docify-1.1.0.dist-info/METADATA
docify-1.1.0.dist-info/WHEEL
docify-1.1.0.dist-info/entry_points.txt
docify-1.1.0.dist-info/licenses/LICENSE
docify.py
docify-1.1.0.dist-info/RECORD
