Metadata-Version: 2.1
Name: docify
Version: 1.1.0
Summary: A script to add docstrings to Python type stubs using reflection
Author-Email: AThePeanut4 <andre.toerien8@gmail.com>
License: MIT
Classifier: Development Status :: 4 - Beta
Classifier: Intended Audience :: Developers
Classifier: License :: OSI Approved :: MIT License
Classifier: Programming Language :: Python :: 3
Classifier: Programming Language :: Python :: 3.8
Classifier: Programming Language :: Python :: 3.9
Classifier: Programming Language :: Python :: 3.10
Classifier: Programming Language :: Python :: 3.11
Classifier: Programming Language :: Python :: 3.12
Classifier: Programming Language :: Python :: 3.13
Classifier: Topic :: Software Development
Classifier: Topic :: Utilities
Project-URL: Repository, https://github.com/AThePeanut4/docify
Requires-Python: >=3.8
Requires-Dist: libcst>=1.1.0
Requires-Dist: tqdm>=4.66.4
